setup.py
slackminion/__init__.py
slackminion/plugins/__init__.py
slackminion/plugins/state_s3/__init__.py
slackminion/plugins/state_s3/handler.py
slackminion_s3.egg-info/PKG-INFO
slackminion_s3.egg-info/SOURCES.txt
slackminion_s3.egg-info/dependency_links.txt
slackminion_s3.egg-info/requires.txt
slackminion_s3.egg-info/top_level.txt