Metadata-Version: 1.1
Name: slackminion-s3
Version: 0.1.0
Summary: Provides a s3 state handler for slackminion
Home-page: https://github.com/arcticfoxnv/slackminion-s3
Author: Nick King
Author-email: UNKNOWN
License: MIT
Platform: UNKNOWN
Classifier: Programming Language :: Python
Classifier: License :: OSI Approved :: MIT License
Classifier: Operating System :: OS Independent
Classifier: Development Status :: 2 - Pre-Alpha
Classifier: Topic :: Communications :: Chat
